ziphttpd/__init__.py
ziphttpd/__main__.py
ziphttpd-1.1.0.dist-info/WHEEL
ziphttpd-1.1.0.dist-info/entry_points.txt
ziphttpd-1.1.0.dist-info/METADATA
ziphttpd-1.1.0.dist-info/RECORD
