Metadata-Version: 2.3
Name: ziphttpd
Version: 1.1.0
Summary: Serve the contents of a Zip file over HTTP.
Author: Benoit Hamelin
Author-email: Benoit Hamelin <benoit@benoithamelin.com>
Requires-Python: >=3.11
